jiml/__init__.py
jiml/__main__.py
jiml/cli.py
jiml/common.py
jiml/config.py
jiml/environment.py
jiml/exceptions.py
jiml/filters.py
jiml/loaders.py
jiml/testlib.py
jiml/validation.py
jiml-0.1.4.dist-info/LICENSE
jiml-0.1.4.dist-info/METADATA
jiml-0.1.4.dist-info/WHEEL
jiml-0.1.4.dist-info/top_level.txt
jiml-0.1.4.dist-info/zip-safe
jiml-0.1.4.dist-info/RECORD
